[
  {
    "inputs": [],
    "name": "ReentrancyGuardReentrantCall",
    "type": "error"
  },
  {
    "anonymous": false,
    "inputs": [
      {
        "indexed": true,
        "internalType": "uint256",
        "name": "tHuntId",
        "type": "uint256"
      },
      {
        "indexed": true,
        "internalType": "address",
        "name": "user",
        "type": "address"
      }
    ],
    "name": "BonusKeyClaimed",
    "type": "event"
  },
  {
    "anonymous": false,
    "inputs": [
      {
        "indexed": true,
        "internalType": "address",
        "name": "user",
        "type": "address"
      },
      {
        "indexed": false,
        "internalType": "uint256",
        "name": "monSpent",
        "type": "uint256"
      },
      {
        "indexed": false,
        "internalType": "uint256",
        "name": "keysReceived",
        "type": "uint256"
      }
    ],
    "name": "KeysPurchased",
    "type": "event"
  },
  {
    "anonymous": false,
    "inputs": [
      {
        "indexed": true,
        "internalType": "uint256",
        "name": "tHuntId",
        "type": "uint256"
      },
      {
        "indexed": false,
        "internalType": "uint64",
        "name": "sequenceNumber",
        "type": "uint64"
      }
    ],
    "name": "RandomnessRequested",
    "type": "event"
  },
  {
    "anonymous": false,
    "inputs": [
      {
        "indexed": true,
        "internalType": "uint256",
        "name": "tHuntId",
        "type": "uint256"
      },
      {
        "indexed": true,
        "internalType": "uint256",
        "name": "squareIndex",
        "type": "uint256"
      },
      {
        "indexed": true,
        "internalType": "address",
        "name": "opener",
        "type": "address"
      }
    ],
    "name": "SquareCommitted",
    "type": "event"
  },
  {
    "anonymous": false,
    "inputs": [
      {
        "indexed": true,
        "internalType": "uint256",
        "name": "tHuntId",
        "type": "uint256"
      },
      {
        "indexed": true,
        "internalType": "uint256",
        "name": "squareIndex",
        "type": "uint256"
      },
      {
        "indexed": true,
        "internalType": "address",
        "name": "opener",
        "type": "address"
      },
      {
        "indexed": false,
        "internalType": "bool",
        "name": "isTreasure",
        "type": "bool"
      }
    ],
    "name": "SquareRevealed",
    "type": "event"
  },
  {
    "anonymous": false,
    "inputs": [
      {
        "indexed": true,
        "internalType": "uint256",
        "name": "tHuntId",
        "type": "uint256"
      },
      {
        "indexed": true,
        "internalType": "uint256",
        "name": "treasureIndex",
        "type": "uint256"
      },
      {
        "indexed": true,
        "internalType": "address",
        "name": "winner",
        "type": "address"
      },
      {
        "indexed": false,
        "internalType": "uint256",
        "name": "reward",
        "type": "uint256"
      }
    ],
    "name": "TreasureClaimed",
    "type": "event"
  },
  {
    "anonymous": false,
    "inputs": [
      {
        "indexed": true,
        "internalType": "uint256",
        "name": "tHuntId",
        "type": "uint256"
      },
      {
        "indexed": true,
        "internalType": "uint256",
        "name": "treasureIndex",
        "type": "uint256"
      },
      {
        "indexed": true,
        "internalType": "address",
        "name": "finder",
        "type": "address"
      },
      {
        "indexed": false,
        "internalType": "uint256",
        "name": "reward",
        "type": "uint256"
      }
    ],
    "name": "TreasureFound",
    "type": "event"
  },
  {
    "anonymous": false,
    "inputs": [
      {
        "indexed": true,
        "internalType": "uint256",
        "name": "tHuntId",
        "type": "uint256"
      }
    ],
    "name": "TreasureHuntActivated",
    "type": "event"
  },
  {
    "anonymous": false,
    "inputs": [
      {
        "indexed": true,
        "internalType": "uint256",
        "name": "tHuntId",
        "type": "uint256"
      },
      {
        "indexed": false,
        "internalType": "string",
        "name": "reason",
        "type": "string"
      }
    ],
    "name": "TreasureHuntCancelled",
    "type": "event"
  },
  {
    "anonymous": false,
    "inputs": [
      {
        "indexed": true,
        "internalType": "uint256",
        "name": "tHuntId",
        "type": "uint256"
      }
    ],
    "name": "TreasureHuntCompleted",
    "type": "event"
  },
  {
    "anonymous": false,
    "inputs": [
      {
        "indexed": true,
        "internalType": "uint256",
        "name": "tHuntId",
        "type": "uint256"
      },
      {
        "indexed": false,
        "internalType": "uint256",
        "name": "gridWidth",
        "type": "uint256"
      },
      {
        "indexed": false,
        "internalType": "uint256",
        "name": "gridHeight",
        "type": "uint256"
      },
      {
        "indexed": false,
        "internalType": "uint256",
        "name": "treasureCount",
        "type": "uint256"
      },
      {
        "indexed": false,
        "internalType": "uint256",
        "name": "rewardPerTreasure",
        "type": "uint256"
      },
      {
        "indexed": false,
        "internalType": "uint256",
        "name": "startTime",
        "type": "uint256"
      },
      {
        "indexed": false,
        "internalType": "uint256",
        "name": "endTime",
        "type": "uint256"
      }
    ],
    "name": "TreasureHuntCreated",
    "type": "event"
  },
  {
    "anonymous": false,
    "inputs": [
      {
        "indexed": true,
        "internalType": "uint256",
        "name": "tHuntId",
        "type": "uint256"
      }
    ],
    "name": "TreasureHuntEnded",
    "type": "event"
  },
  {
    "anonymous": false,
    "inputs": [
      {
        "indexed": false,
        "internalType": "uint256",
        "name": "amount",
        "type": "uint256"
      }
    ],
    "name": "TreasuryTransfer",
    "type": "event"
  },
  {
    "inputs": [],
    "name": "ADMIN",
    "outputs": [
      {
        "internalType": "address",
        "name": "",
        "type": "address"
      }
    ],
    "stateMutability": "view",
    "type": "function"
  },
  {
    "inputs": [],
    "name": "CLAIM_WINDOW",
    "outputs": [
      {
        "internalType": "uint256",
        "name": "",
        "type": "uint256"
      }
    ],
    "stateMutability": "view",
    "type": "function"
  },
  {
    "inputs": [],
    "name": "KEYS_PER_MON",
    "outputs": [
      {
        "internalType": "uint256",
        "name": "",
        "type": "uint256"
      }
    ],
    "stateMutability": "view",
    "type": "function"
  },
  {
    "inputs": [],
    "name": "MAX_GRID_SIZE",
    "outputs": [
      {
        "internalType": "uint256",
        "name": "",
        "type": "uint256"
      }
    ],
    "stateMutability": "view",
    "type": "function"
  },
  {
    "inputs": [],
    "name": "MAX_KEY_PURCHASE",
    "outputs": [
      {
        "internalType": "uint256",
        "name": "",
        "type": "uint256"
      }
    ],
    "stateMutability": "view",
    "type": "function"
  },
  {
    "inputs": [],
    "name": "MIN_KEY_PURCHASE",
    "outputs": [
      {
        "internalType": "uint256",
        "name": "",
        "type": "uint256"
      }
    ],
    "stateMutability": "view",
    "type": "function"
  },
  {
    "inputs": [],
    "name": "ONEMON_CONTRACT",
    "outputs": [
      {
        "internalType": "contract IOneMON",
        "name": "",
        "type": "address"
      }
    ],
    "stateMutability": "view",
    "type": "function"
  },
  {
    "inputs": [],
    "name": "PYTH_ENTROPY",
    "outputs": [
      {
        "internalType": "contract IEntropy",
        "name": "",
        "type": "address"
      }
    ],
    "stateMutability": "view",
    "type": "function"
  },
  {
    "inputs": [],
    "name": "TREASURY",
    "outputs": [
      {
        "internalType": "address",
        "name": "",
        "type": "address"
      }
    ],
    "stateMutability": "view",
    "type": "function"
  },
  {
    "inputs": [],
    "name": "VRF_TIMEOUT",
    "outputs": [
      {
        "internalType": "uint256",
        "name": "",
        "type": "uint256"
      }
    ],
    "stateMutability": "view",
    "type": "function"
  },
  {
    "inputs": [
      {
        "internalType": "uint64",
        "name": "sequence",
        "type": "uint64"
      },
      {
        "internalType": "address",
        "name": "provider",
        "type": "address"
      },
      {
        "internalType": "bytes32",
        "name": "randomNumber",
        "type": "bytes32"
      }
    ],
    "name": "_entropyCallback",
    "outputs": [],
    "stateMutability": "nonpayable",
    "type": "function"
  },
  {
    "inputs": [
      {
        "internalType": "uint256",
        "name": "",
        "type": "uint256"
      }
    ],
    "name": "activeTHuntIds",
    "outputs": [
      {
        "internalType": "uint256",
        "name": "",
        "type": "uint256"
      }
    ],
    "stateMutability": "view",
    "type": "function"
  },
  {
    "inputs": [
      {
        "internalType": "uint256",
        "name": "",
        "type": "uint256"
      },
      {
        "internalType": "address",
        "name": "",
        "type": "address"
      }
    ],
    "name": "bonusKeyClaimed",
    "outputs": [
      {
        "internalType": "bool",
        "name": "",
        "type": "bool"
      }
    ],
    "stateMutability": "view",
    "type": "function"
  },
  {
    "inputs": [],
    "name": "buyKeys",
    "outputs": [],
    "stateMutability": "payable",
    "type": "function"
  },
  {
    "inputs": [
      {
        "internalType": "uint256",
        "name": "tHuntId",
        "type": "uint256"
      },
      {
        "internalType": "address",
        "name": "user",
        "type": "address"
      }
    ],
    "name": "canClaimBonusKey",
    "outputs": [
      {
        "internalType": "bool",
        "name": "",
        "type": "bool"
      }
    ],
    "stateMutability": "view",
    "type": "function"
  },
  {
    "inputs": [
      {
        "internalType": "uint256",
        "name": "tHuntId",
        "type": "uint256"
      },
      {
        "internalType": "uint256",
        "name": "treasureIndex",
        "type": "uint256"
      },
      {
        "internalType": "address",
        "name": "user",
        "type": "address"
      }
    ],
    "name": "canClaimTreasure",
    "outputs": [
      {
        "internalType": "bool",
        "name": "",
        "type": "bool"
      }
    ],
    "stateMutability": "view",
    "type": "function"
  },
  {
    "inputs": [
      {
        "internalType": "uint256",
        "name": "tHuntId",
        "type": "uint256"
      }
    ],
    "name": "claimBonusKey",
    "outputs": [],
    "stateMutability": "nonpayable",
    "type": "function"
  },
  {
    "inputs": [
      {
        "internalType": "uint256",
        "name": "tHuntId",
        "type": "uint256"
      },
      {
        "internalType": "uint256",
        "name": "treasureIndex",
        "type": "uint256"
      }
    ],
    "name": "claimTreasure",
    "outputs": [],
    "stateMutability": "nonpayable",
    "type": "function"
  },
  {
    "inputs": [
      {
        "internalType": "uint256",
        "name": "tHuntId",
        "type": "uint256"
      },
      {
        "internalType": "uint256",
        "name": "squareIndex",
        "type": "uint256"
      },
      {
        "internalType": "bytes32",
        "name": "commitHash",
        "type": "bytes32"
      }
    ],
    "name": "commitSquare",
    "outputs": [],
    "stateMutability": "nonpayable",
    "type": "function"
  },
  {
    "inputs": [
      {
        "internalType": "uint256",
        "name": "gridWidth",
        "type": "uint256"
      },
      {
        "internalType": "uint256",
        "name": "gridHeight",
        "type": "uint256"
      },
      {
        "internalType": "uint256",
        "name": "rewardPerTreasure",
        "type": "uint256"
      },
      {
        "internalType": "uint256",
        "name": "treasureCount",
        "type": "uint256"
      },
      {
        "internalType": "uint256",
        "name": "startTime",
        "type": "uint256"
      },
      {
        "internalType": "uint256",
        "name": "endTime",
        "type": "uint256"
      },
      {
        "internalType": "uint256",
        "name": "raffleIdStart",
        "type": "uint256"
      },
      {
        "internalType": "uint256",
        "name": "raffleIdEnd",
        "type": "uint256"
      }
    ],
    "name": "createTreasureHunt",
    "outputs": [],
    "stateMutability": "nonpayable",
    "type": "function"
  },
  {
    "inputs": [
      {
        "internalType": "uint256",
        "name": "tHuntId",
        "type": "uint256"
      }
    ],
    "name": "endTreasureHunt",
    "outputs": [],
    "stateMutability": "nonpayable",
    "type": "function"
  },
  {
    "inputs": [
      {
        "internalType": "uint256",
        "name": "tHuntId",
        "type": "uint256"
      }
    ],
    "name": "forceCancel",
    "outputs": [],
    "stateMutability": "nonpayable",
    "type": "function"
  },
  {
    "inputs": [],
    "name": "getActiveTHuntCount",
    "outputs": [
      {
        "internalType": "uint256",
        "name": "",
        "type": "uint256"
      }
    ],
    "stateMutability": "view",
    "type": "function"
  },
  {
    "inputs": [],
    "name": "getActiveTHuntIds",
    "outputs": [
      {
        "internalType": "uint256[]",
        "name": "",
        "type": "uint256[]"
      }
    ],
    "stateMutability": "view",
    "type": "function"
  },
  {
    "inputs": [
      {
        "internalType": "address",
        "name": "user",
        "type": "address"
      }
    ],
    "name": "getKeyBalance",
    "outputs": [
      {
        "internalType": "uint256",
        "name": "",
        "type": "uint256"
      }
    ],
    "stateMutability": "view",
    "type": "function"
  },
  {
    "inputs": [],
    "name": "getReservedFunds",
    "outputs": [
      {
        "internalType": "uint256",
        "name": "reserved",
        "type": "uint256"
      }
    ],
    "stateMutability": "view",
    "type": "function"
  },
  {
    "inputs": [
      {
        "internalType": "uint256",
        "name": "tHuntId",
        "type": "uint256"
      }
    ],
    "name": "getReservedSquareCount",
    "outputs": [
      {
        "internalType": "uint256",
        "name": "",
        "type": "uint256"
      }
    ],
    "stateMutability": "view",
    "type": "function"
  },
  {
    "inputs": [
      {
        "internalType": "uint256",
        "name": "tHuntId",
        "type": "uint256"
      }
    ],
    "name": "getReservedSquares",
    "outputs": [
      {
        "internalType": "uint256[]",
        "name": "",
        "type": "uint256[]"
      }
    ],
    "stateMutability": "view",
    "type": "function"
  },
  {
    "inputs": [
      {
        "internalType": "uint256",
        "name": "tHuntId",
        "type": "uint256"
      }
    ],
    "name": "getRevealedSquareCount",
    "outputs": [
      {
        "internalType": "uint256",
        "name": "",
        "type": "uint256"
      }
    ],
    "stateMutability": "view",
    "type": "function"
  },
  {
    "inputs": [
      {
        "internalType": "uint256",
        "name": "tHuntId",
        "type": "uint256"
      }
    ],
    "name": "getRevealedSquaresWithResults",
    "outputs": [
      {
        "internalType": "uint256[]",
        "name": "revealedIndices",
        "type": "uint256[]"
      },
      {
        "internalType": "bool[]",
        "name": "isTreasure",
        "type": "bool[]"
      },
      {
        "internalType": "address[]",
        "name": "openers",
        "type": "address[]"
      }
    ],
    "stateMutability": "view",
    "type": "function"
  },
  {
    "inputs": [
      {
        "internalType": "uint256",
        "name": "tHuntId",
        "type": "uint256"
      },
      {
        "internalType": "uint256",
        "name": "squareIndex",
        "type": "uint256"
      }
    ],
    "name": "getSquareOpener",
    "outputs": [
      {
        "internalType": "address",
        "name": "",
        "type": "address"
      }
    ],
    "stateMutability": "view",
    "type": "function"
  },
  {
    "inputs": [
      {
        "internalType": "uint256",
        "name": "tHuntId",
        "type": "uint256"
      }
    ],
    "name": "getTHuntInfo",
    "outputs": [
      {
        "internalType": "uint256",
        "name": "gridWidth",
        "type": "uint256"
      },
      {
        "internalType": "uint256",
        "name": "gridHeight",
        "type": "uint256"
      },
      {
        "internalType": "uint256",
        "name": "rewardPerTreasure",
        "type": "uint256"
      },
      {
        "internalType": "uint256",
        "name": "treasureCount",
        "type": "uint256"
      },
      {
        "internalType": "uint256",
        "name": "startTime",
        "type": "uint256"
      },
      {
        "internalType": "uint256",
        "name": "endTime",
        "type": "uint256"
      },
      {
        "internalType": "uint256",
        "name": "raffleIdStart",
        "type": "uint256"
      },
      {
        "internalType": "uint256",
        "name": "raffleIdEnd",
        "type": "uint256"
      },
      {
        "internalType": "uint256",
        "name": "treasuresFound",
        "type": "uint256"
      },
      {
        "internalType": "uint256",
        "name": "treasuresClaimed",
        "type": "uint256"
      },
      {
        "internalType": "uint256",
        "name": "claimDeadline",
        "type": "uint256"
      },
      {
        "internalType": "enum TreasureHunt.THuntState",
        "name": "state",
        "type": "uint8"
      }
    ],
    "stateMutability": "view",
    "type": "function"
  },
  {
    "inputs": [
      {
        "internalType": "uint256",
        "name": "tHuntId",
        "type": "uint256"
      },
      {
        "internalType": "address",
        "name": "user",
        "type": "address"
      }
    ],
    "name": "getUserTHuntStatus",
    "outputs": [
      {
        "internalType": "uint256",
        "name": "userKeyBalance",
        "type": "uint256"
      },
      {
        "internalType": "bool",
        "name": "hasBonusKey",
        "type": "bool"
      },
      {
        "internalType": "bool",
        "name": "canClaimBonus",
        "type": "bool"
      },
      {
        "internalType": "uint256",
        "name": "treasuresWon",
        "type": "uint256"
      },
      {
        "internalType": "uint256",
        "name": "treasuresClaimed_",
        "type": "uint256"
      }
    ],
    "stateMutability": "view",
    "type": "function"
  },
  {
    "inputs": [
      {
        "internalType": "uint256",
        "name": "tHuntId",
        "type": "uint256"
      },
      {
        "internalType": "address",
        "name": "user",
        "type": "address"
      }
    ],
    "name": "getUserTreasures",
    "outputs": [
      {
        "internalType": "uint256[]",
        "name": "wonTreasureIds",
        "type": "uint256[]"
      },
      {
        "internalType": "uint256[]",
        "name": "claimableTreasureIds",
        "type": "uint256[]"
      },
      {
        "internalType": "uint256[]",
        "name": "claimedTreasureIds",
        "type": "uint256[]"
      }
    ],
    "stateMutability": "view",
    "type": "function"
  },
  {
    "inputs": [],
    "name": "getWithdrawableAmount",
    "outputs": [
      {
        "internalType": "uint256",
        "name": "",
        "type": "uint256"
      }
    ],
    "stateMutability": "view",
    "type": "function"
  },
  {
    "inputs": [
      {
        "internalType": "uint256",
        "name": "tHuntId",
        "type": "uint256"
      },
      {
        "internalType": "uint256",
        "name": "squareIndex",
        "type": "uint256"
      }
    ],
    "name": "isSquareReserved",
    "outputs": [
      {
        "internalType": "bool",
        "name": "",
        "type": "bool"
      }
    ],
    "stateMutability": "view",
    "type": "function"
  },
  {
    "inputs": [
      {
        "internalType": "uint256",
        "name": "tHuntId",
        "type": "uint256"
      },
      {
        "internalType": "uint256",
        "name": "squareIndex",
        "type": "uint256"
      }
    ],
    "name": "isSquareRevealed",
    "outputs": [
      {
        "internalType": "bool",
        "name": "",
        "type": "bool"
      }
    ],
    "stateMutability": "view",
    "type": "function"
  },
  {
    "inputs": [
      {
        "internalType": "address",
        "name": "",
        "type": "address"
      }
    ],
    "name": "keyBalance",
    "outputs": [
      {
        "internalType": "uint256",
        "name": "",
        "type": "uint256"
      }
    ],
    "stateMutability": "view",
    "type": "function"
  },
  {
    "inputs": [
      {
        "internalType": "uint256",
        "name": "tHuntId",
        "type": "uint256"
      }
    ],
    "name": "markCompleted",
    "outputs": [],
    "stateMutability": "nonpayable",
    "type": "function"
  },
  {
    "inputs": [],
    "name": "nextTHuntId",
    "outputs": [
      {
        "internalType": "uint256",
        "name": "",
        "type": "uint256"
      }
    ],
    "stateMutability": "view",
    "type": "function"
  },
  {
    "inputs": [
      {
        "internalType": "uint256",
        "name": "",
        "type": "uint256"
      }
    ],
    "name": "reservedSquareCount",
    "outputs": [
      {
        "internalType": "uint256",
        "name": "",
        "type": "uint256"
      }
    ],
    "stateMutability": "view",
    "type": "function"
  },
  {
    "inputs": [
      {
        "internalType": "uint256",
        "name": "tHuntId",
        "type": "uint256"
      },
      {
        "internalType": "uint256",
        "name": "squareIndex",
        "type": "uint256"
      },
      {
        "internalType": "bytes32",
        "name": "secret",
        "type": "bytes32"
      }
    ],
    "name": "revealSquare",
    "outputs": [],
    "stateMutability": "nonpayable",
    "type": "function"
  },
  {
    "inputs": [
      {
        "internalType": "uint256",
        "name": "",
        "type": "uint256"
      }
    ],
    "name": "revealedSquareCount",
    "outputs": [
      {
        "internalType": "uint256",
        "name": "",
        "type": "uint256"
      }
    ],
    "stateMutability": "view",
    "type": "function"
  },
  {
    "inputs": [
      {
        "internalType": "uint256",
        "name": "",
        "type": "uint256"
      },
      {
        "internalType": "uint256",
        "name": "",
        "type": "uint256"
      }
    ],
    "name": "squareCommitHash",
    "outputs": [
      {
        "internalType": "bytes32",
        "name": "",
        "type": "bytes32"
      }
    ],
    "stateMutability": "view",
    "type": "function"
  },
  {
    "inputs": [
      {
        "internalType": "uint256",
        "name": "",
        "type": "uint256"
      },
      {
        "internalType": "uint256",
        "name": "",
        "type": "uint256"
      }
    ],
    "name": "squareOpener",
    "outputs": [
      {
        "internalType": "address",
        "name": "",
        "type": "address"
      }
    ],
    "stateMutability": "view",
    "type": "function"
  },
  {
    "inputs": [
      {
        "internalType": "uint256",
        "name": "",
        "type": "uint256"
      },
      {
        "internalType": "uint256",
        "name": "",
        "type": "uint256"
      }
    ],
    "name": "squareReserved",
    "outputs": [
      {
        "internalType": "bool",
        "name": "",
        "type": "bool"
      }
    ],
    "stateMutability": "view",
    "type": "function"
  },
  {
    "inputs": [
      {
        "internalType": "uint256",
        "name": "",
        "type": "uint256"
      },
      {
        "internalType": "uint256",
        "name": "",
        "type": "uint256"
      }
    ],
    "name": "squareRevealed",
    "outputs": [
      {
        "internalType": "bool",
        "name": "",
        "type": "bool"
      }
    ],
    "stateMutability": "view",
    "type": "function"
  },
  {
    "inputs": [
      {
        "internalType": "uint256",
        "name": "",
        "type": "uint256"
      }
    ],
    "name": "tHuntIdToActiveIndex",
    "outputs": [
      {
        "internalType": "uint256",
        "name": "",
        "type": "uint256"
      }
    ],
    "stateMutability": "view",
    "type": "function"
  },
  {
    "inputs": [
      {
        "internalType": "uint256",
        "name": "",
        "type": "uint256"
      },
      {
        "internalType": "uint256",
        "name": "",
        "type": "uint256"
      }
    ],
    "name": "treasureClaimed",
    "outputs": [
      {
        "internalType": "bool",
        "name": "",
        "type": "bool"
      }
    ],
    "stateMutability": "view",
    "type": "function"
  },
  {
    "inputs": [
      {
        "internalType": "uint256",
        "name": "",
        "type": "uint256"
      }
    ],
    "name": "treasureHunts",
    "outputs": [
      {
        "internalType": "uint256",
        "name": "gridWidth",
        "type": "uint256"
      },
      {
        "internalType": "uint256",
        "name": "gridHeight",
        "type": "uint256"
      },
      {
        "internalType": "uint256",
        "name": "rewardPerTreasure",
        "type": "uint256"
      },
      {
        "internalType": "uint256",
        "name": "treasureCount",
        "type": "uint256"
      },
      {
        "internalType": "uint256",
        "name": "startTime",
        "type": "uint256"
      },
      {
        "internalType": "uint256",
        "name": "endTime",
        "type": "uint256"
      },
      {
        "internalType": "uint256",
        "name": "raffleIdStart",
        "type": "uint256"
      },
      {
        "internalType": "uint256",
        "name": "raffleIdEnd",
        "type": "uint256"
      },
      {
        "internalType": "bytes32",
        "name": "treasureSeed",
        "type": "bytes32"
      },
      {
        "internalType": "uint256",
        "name": "vrfRequestTime",
        "type": "uint256"
      },
      {
        "internalType": "uint256",
        "name": "treasuresFound",
        "type": "uint256"
      },
      {
        "internalType": "uint256",
        "name": "treasuresClaimed",
        "type": "uint256"
      },
      {
        "internalType": "uint256",
        "name": "claimDeadline",
        "type": "uint256"
      },
      {
        "internalType": "enum TreasureHunt.THuntState",
        "name": "state",
        "type": "uint8"
      }
    ],
    "stateMutability": "view",
    "type": "function"
  },
  {
    "inputs": [
      {
        "internalType": "uint256",
        "name": "",
        "type": "uint256"
      },
      {
        "internalType": "uint256",
        "name": "",
        "type": "uint256"
      }
    ],
    "name": "treasureWinner",
    "outputs": [
      {
        "internalType": "address",
        "name": "",
        "type": "address"
      }
    ],
    "stateMutability": "view",
    "type": "function"
  },
  {
    "inputs": [
      {
        "internalType": "uint256",
        "name": "amount",
        "type": "uint256"
      }
    ],
    "name": "treasuryTransfer",
    "outputs": [],
    "stateMutability": "nonpayable",
    "type": "function"
  },
  {
    "inputs": [
      {
        "internalType": "uint64",
        "name": "",
        "type": "uint64"
      }
    ],
    "name": "vrfRequestToTHunt",
    "outputs": [
      {
        "internalType": "uint256",
        "name": "",
        "type": "uint256"
      }
    ],
    "stateMutability": "view",
    "type": "function"
  },
  {
    "stateMutability": "payable",
    "type": "receive"
  }
]
